aliyunsdkconfig/__init__.py
aliyunsdkconfig/endpoint.py
aliyunsdkconfig/request/__init__.py
aliyunsdkconfig/request/v20200907/ActiveAggregateConfigRulesRequest.py
aliyunsdkconfig/request/v20200907/ActiveConfigRulesRequest.py
aliyunsdkconfig/request/v20200907/AttachAggregateConfigRuleToCompliancePackRequest.py
aliyunsdkconfig/request/v20200907/AttachConfigRuleToCompliancePackRequest.py
aliyunsdkconfig/request/v20200907/CopyCompliancePacksRequest.py
aliyunsdkconfig/request/v20200907/CopyConfigRulesRequest.py
aliyunsdkconfig/request/v20200907/CreateAdvancedSearchFileRequest.py
aliyunsdkconfig/request/v20200907/CreateAggregateAdvancedSearchFileRequest.py
aliyunsdkconfig/request/v20200907/CreateAggregateCompliancePackRequest.py
aliyunsdkconfig/request/v20200907/CreateAggregateConfigDeliveryChannelRequest.py
aliyunsdkconfig/request/v20200907/CreateAggregateConfigRuleRequest.py
aliyunsdkconfig/request/v20200907/CreateAggregateRemediationRequest.py
aliyunsdkconfig/request/v20200907/CreateAggregatorRequest.py
aliyunsdkconfig/request/v20200907/CreateCompliancePackRequest.py
aliyunsdkconfig/request/v20200907/CreateConfigDeliveryChannelRequest.py
aliyunsdkconfig/request/v20200907/CreateConfigRuleRequest.py
aliyunsdkconfig/request/v20200907/CreateDeliveryChannelRequest.py
aliyunsdkconfig/request/v20200907/CreateRemediationRequest.py
aliyunsdkconfig/request/v20200907/DeactiveAggregateConfigRulesRequest.py
aliyunsdkconfig/request/v20200907/DeactiveConfigRulesRequest.py
aliyunsdkconfig/request/v20200907/DeleteAggregateCompliancePacksRequest.py
aliyunsdkconfig/request/v20200907/DeleteAggregateConfigDeliveryChannelRequest.py
aliyunsdkconfig/request/v20200907/DeleteAggregateConfigRulesRequest.py
aliyunsdkconfig/request/v20200907/DeleteAggregateRemediationsRequest.py
aliyunsdkconfig/request/v20200907/DeleteAggregatorsRequest.py
aliyunsdkconfig/request/v20200907/DeleteCompliancePacksRequest.py
aliyunsdkconfig/request/v20200907/DeleteConfigDeliveryChannelRequest.py
aliyun_python_sdk_config-2.2.14.dist-info/LICENSE
aliyun_python_sdk_config-2.2.14.dist-info/METADATA
aliyun_python_sdk_config-2.2.14.dist-info/WHEEL
aliyun_python_sdk_config-2.2.14.dist-info/top_level.txt
aliyun_python_sdk_config-2.2.14.dist-info/RECORD
